dyalog_kernel/__init__.py
dyalog_kernel/__main__.py
dyalog_kernel/install.py
dyalog_kernel/kernel.py
dyalog_kernel/dyalog_apl/kernel.js
dyalog_kernel/dyalog_apl/kernel.json
dyalog_kernel/kernelspec/kernel.js
dyalog_kernel/kernelspec/kernel.json
dyalog_jupyter_kernel-2.0.2.dist-info/LICENSE
dyalog_jupyter_kernel-2.0.2.dist-info/METADATA
dyalog_jupyter_kernel-2.0.2.dist-info/WHEEL
dyalog_jupyter_kernel-2.0.2.dist-info/top_level.txt
dyalog_jupyter_kernel-2.0.2.dist-info/RECORD
