Metadata-Version: 2.1
Name: dyalog-jupyter-kernel
Version: 2.0.2
Summary: Jupyter kernel for Dyalog APL
Home-page: https://github.com/Dyalog/dyalog-jupyter-kernel
Author: Stefan Kruger
Author-email: stefan@dyalog.com
Classifier: Programming Language :: Python :: 3
Classifier: License :: OSI Approved :: MIT License
Classifier: Operating System :: OS Independent
Requires-Python: >=3.8
License-File: LICENSE
Requires-Dist: ipykernel (>=6.20.0)
